D_flipflop/dff.v
module dff(
    input D, 
    input reset, 
    input clk, 
    output q_bar, 
    output reg q
);
    assign q_bar = ~q;
    
    always @(posedge clk or posedge reset) begin
        if (reset) begin
            q <= 0;
        end else begin
            q <= D;
        end
    end
endmodule

D_flipflop/dff_tb.v
`timescale 1ns/1ps

module dff_tb;
    reg D;
    reg reset;
    reg clk;
    wire q;
    wire q_bar;

    // Instantiate the D flip-flop module
    dff uut (
        .D(D),
        .reset(reset),
        .clk(clk),
        .q(q),
        .q_bar(q_bar)
    );

    // Clock generation
    initial begin
        clk = 0;
        forever #10 clk = #1 ~clk; // 10ns clock period
    end

    // Stimulus generation
    initial begin
        // Initialize signals
        D = #100 0;
        reset = #100 0;

        // Apply reset
        reset = #100 1;
        #1000;
        reset = #100 0;

        // Apply test stimulus
        #1000 D = #100 1;
        #1000 D = #100 0;
        #1000 D = #100 1;
        #2000 D = #100 0;
        
        // Apply reset again
        reset = #100 1;
        #1000;
        reset = #100 0;

        // Continue stimulus
        #1000 D = #100 1;
        #1000 D = #100 0;
        #2000;

        // Finish simulation
        $finish;
    end

    // Dump waveform
    initial begin
        $dumpfile("dff_tb.vcd");
        $dumpvars(0, dff_tb);
    end

endmodule

D_flipflop/dff_tb.vcd
$date
	Wed Jun 19 22:50:49 2024
$end
$version
	Icarus Verilog
$end
$timescale
	1ps
$end
$scope module dff_tb $end
$var wire 1 ! q_bar $end
$var wire 1 " q $end
$var reg 1 # D $end
$var reg 1 $ clk $end
$var reg 1 % reset $end
$scope module uut $end
$var wire 1 # D $end
$var wire 1 $ clk $end
$var wire 1 ! q_bar $end
$var wire 1 % reset $end
$var reg 1 " q $end
$upscope $end
$upscope $end
$enddefinitions $end
$comment Show the parameter values. $end
$dumpall
$end
#0
$dumpvars
x%
0$
x#
x"
x!
$end
#11000
1$
#22000
0$
#33000
1$
#44000
0$
#55000
1$
#66000
0$
#77000
1$
#88000
0$
#99000
1$
#100000
0#
#110000
0$
#121000
1!
0"
1$
#132000
0$
#143000
1$
#154000
0$
#165000
1$
#176000
0$
#187000
1$
#198000
0$
#200000
0%
#209000
1$
#220000
0$
#231000
1$
#242000
0$
#253000
1$
#264000
0$
#275000
1$
#286000
0$
#297000
1$
#300000
1%
#308000
0$
#319000
1$
#330000
0$
#341000
1$
#352000
0$
#363000
1$
#374000
0$
#385000
1$
#396000
0$
#407000
1$
#418000
0$
#429000
1$
#440000
0$
#451000
1$
#462000
0$
#473000
1$
#484000
0$
#495000
1$
#506000
0$
#517000
1$
#528000
0$
#539000
1$
#550000
0$
#561000
1$
#572000
0$
#583000
1$
#594000
0$
#605000
1$
#616000
0$
#627000
1$
#638000
0$
#649000
1$
#660000
0$
#671000
1$
#682000
0$
#693000
1$
#704000
0$
#715000
1$
#726000
0$
#737000
1$
#748000
0$
#759000
1$
#770000
0$
#781000
1$
#792000
0$
#803000
1$
#814000
0$
#825000
1$
#836000
0$
#847000
1$
#858000
0$
#869000
1$
#880000
0$
#891000
1$
#902000
0$
#913000
1$
#924000
0$
#935000
1$
#946000
0$
#957000
1$
#968000
0$
#979000
1$
#990000
0$
#1001000
1$
#1012000
0$
#1023000
1$
#1034000
0$
#1045000
1$
#1056000
0$
#1067000
1$
#1078000
0$
#1089000
1$
#1100000
0$
#1111000
1$
#1122000
0$
#1133000
1$
#1144000
0$
#1155000
1$
#1166000
0$
#1177000
1$
#1188000
0$
#1199000
1$
#1210000
0$
#1221000
1$
#1232000
0$
#1243000
1$
#1254000
0$
#1265000
1$
#1276000
0$
#1287000
1$
#1298000
0$
#1309000
1$
#1320000
0$
#1331000
1$
#1342000
0$
#1353000
1$
#1364000
0$
#1375000
1$
#1386000
0$
#1397000
1$
#1400000
0%
#1408000
0$
#1419000
1$
#1430000
0$
#1441000
1$
#1452000
0$
#1463000
1$
#1474000
0$
#1485000
1$
#1496000
0$
#1507000
1$
#1518000
0$
#1529000
1$
#1540000
0$
#1551000
1$
#1562000
0$
#1573000
1$
#1584000
0$
#1595000
1$
#1606000
0$
#1617000
1$
#1628000
0$
#1639000
1$
#1650000
0$
#1661000
1$
#1672000
0$
#1683000
1$
#1694000
0$
#1705000
1$
#1716000
0$
#1727000
1$
#1738000
0$
#1749000
1$
#1760000
0$
#1771000
1$
#1782000
0$
#1793000
1$
#1804000
0$
#1815000
1$
#1826000
0$
#1837000
1$
#1848000
0$
#1859000
1$
#1870000
0$
#1881000
1$
#1892000
0$
#1903000
1$
#1914000
0$
#1925000
1$
#1936000
0$
#1947000
1$
#1958000
0$
#1969000
1$
#1980000
0$
#1991000
1$
#2002000
0$
#2013000
1$
#2024000
0$
#2035000
1$
#2046000
0$
#2057000
1$
#2068000
0$
#2079000
1$
#2090000
0$
#2101000
1$
#2112000
0$
#2123000
1$
#2134000
0$
#2145000
1$
#2156000
0$
#2167000
1$
#2178000
0$
#2189000
1$
#2200000
0$
#2211000
1$
#2222000
0$
#2233000
1$
#2244000
0$
#2255000
1$
#2266000
0$
#2277000
1$
#2288000
0$
#2299000
1$
#2310000
0$
#2321000
1$
#2332000
0$
#2343000
1$
#2354000
0$
#2365000
1$
#2376000
0$
#2387000
1$
#2398000
0$
#2409000
1$
#2420000
0$
#2431000
1$
#2442000
0$
#2453000
1$
#2464000
0$
#2475000
1$
#2486000
0$
#2497000
1$
#2500000
1#
#2508000
0$
#2519000
0!
1"
1$
