wave_generator/generator.v
module generator (
    input wire clk,
    output reg [11:0] wave
);
    reg [11:0] wave_data [0:9999]; // Array to hold the wave data
    integer i;

    initial begin
        $readmemh("wave.mem", wave_data); // Read memory file
        i = 0;
    end

    always @(posedge clk) begin
        wave <= wave_data[i];
        i <= i + 1;
        if (i == 10000) // Reset index if end of data
            i <= 0;
    end
endmodule

wave_generator/tb_wave_generator.v
`timescale 100us/1ns

module tb_wave_generator;
    reg clk;
    wire [11:0] wave;

    // Instantiate the wave generator
    generator wg (
        .clk(clk),
        .wave(wave)
    );

    // Clock generation: 1 MHz clock (period = 1 us = 5 * 200 ns)
    initial begin
        clk = 0;
        forever #5 clk = ~clk; // 2.5 * 200 ns high, 2.5 * 200 ns low -> 1 MHz
    end

    // Monitor the wave output
    initial begin
        $dumpfile("wave.vcd");
        $dumpvars(0, tb_wave_generator);
        #100000 $finish;
    end
endmodule

wave_generator/wave.vcd
$date
	Thu Jun 20 14:09:26 2024
$end
$version
	Icarus Verilog
$end
$timescale
	1ns
$end
$scope module tb_wave_generator $end
$var wire 12 ! wave [11:0] $end
$var reg 1 " clk $end
$scope module wg $end
$var wire 1 " clk $end
$var reg 12 # wave [11:0] $end
$var integer 32 $ i [31:0] $end
$upscope $end
$upscope $end
$enddefinitions $end
$comment Show the parameter values. $end
$dumpall
$end
#0
$dumpvars
b0 $
bx #
0"
bx !
$end
#500000
b1 $
b0 !
b0 #
1"
#1000000
0"
#1500000
b10 $
b101100111101 !
b101100111101 #
1"
#2000000
0"
#2500000
b11 $
b100110111111 !
b100110111111 #
1"
#3000000
0"
#3500000
b100 $
b100111000000 !
b100111000000 #
1"
#4000000
0"
#4500000
b101 $
b101101000010 !
b101101000010 #
1"
#5000000
0"
#5500000
b110 $
b110 !
b110 #
1"
#6000000
0"
#6500000
b111 $
b10011001011 !
b10011001011 #
1"
#7000000
0"
#7500000
b1000 $
b11001001011 !
b11001001011 #
1"
#8000000
0"
#8500000
b1001 $
b11001001001 !
b11001001001 #
1"
#9000000
0"
#9500000
b1010 $
b10011000111 !
b10011000111 #
1"
#10000000
0"
#10500000
b1011 $
b0 !
b0 #
1"
#11000000
0"
#11500000
b1100 $
b101100111001 !
b101100111001 #
1"
#12000000
0"
#12500000
b1101 $
b100110110111 !
b100110110111 #
1"
#13000000
0"
#13500000
b1110 $
b100110110101 !
b100110110101 #
1"
#14000000
0"
#14500000
b1111 $
b101100110101 !
b101100110101 #
1"
#15000000
0"
#15500000
b10000 $
b111111111010 !
b111111111010 #
1"
#16000000
0"
#16500000
b10001 $
b10010111110 !
b10010111110 #
1"
#17000000
0"
#17500000
b10010 $
b11001000000 !
b11001000000 #
1"
#18000000
0"
#18500000
b10011 $
b11001000001 !
b11001000001 #
1"
#19000000
0"
#19500000
b10100 $
b10011000011 !
b10011000011 #
1"
#20000000
0"
#20500000
b10101 $
b0 !
b0 #
1"
#21000000
0"
#21500000
b10110 $
b101100111101 !
b101100111101 #
1"
#22000000
0"
#22500000
b10111 $
b100110111111 !
b100110111111 #
1"
#23000000
0"
#23500000
b11000 $
b100111000000 !
b100111000000 #
1"
#24000000
0"
#24500000
b11001 $
b101101000010 !
b101101000010 #
1"
#25000000
0"
#25500000
b11010 $
b110 !
b110 #
1"
#26000000
0"
#26500000
b11011 $
b10011001011 !
b10011001011 #
1"
#27000000
0"
#27500000
b11100 $
b11001001011 !
b11001001011 #
1"
#28000000
0"
#28500000
b11101 $
b11001001001 !
b11001001001 #
1"
#29000000
0"
#29500000
b11110 $
b10011000111 !
b10011000111 #
1"
#30000000
0"
#30500000
b11111 $
b0 !
b0 #
1"
#31000000
0"
#31500000
b100000 $
b101100111001 !
b101100111001 #
1"
#32000000
0"
#32500000
b100001 $
b100110110111 !
b100110110111 #
1"
#33000000
0"
#33500000
b100010 $
b100110110101 !
b100110110101 #
1"
#34000000
0"
#34500000
b100011 $
b101100110101 !
b101100110101 #
1"
#35000000
0"
#35500000
b100100 $
b111111111010 !
b111111111010 #
1"
#36000000
0"
#36500000
b100101 $
b10010111110 !
b10010111110 #
1"
#37000000
0"
#37500000
b100110 $
b11001000000 !
b11001000000 #
1"
#38000000
0"
#38500000
b100111 $
b11001000001 !
b11001000001 #
1"
#39000000
0"
#39500000
b101000 $
b10011000011 !
b10011000011 #
1"
#40000000
0"
#40500000
b101001 $
b0 !
b0 #
1"
#41000000
0"
#41500000
b101010 $
b101100111101 !
b101100111101 #
1"
#42000000
0"
#42500000
b101011 $
b100110111111 !
b100110111111 #
1"
#43000000
0"
#43500000
b101100 $
b100111000000 !
b100111000000 #
1"
#44000000
0"
#44500000
b101101 $
b101101000010 !
b101101000010 #
1"
#45000000
0"
#45500000
b101110 $
b110 !
b110 #
1"
#46000000
0"
#46500000
b101111 $
b10011001011 !
b10011001011 #
1"
#47000000
0"
#47500000
b110000 $
b11001001011 !
b11001001011 #
1"
#48000000
0"
#48500000
b110001 $
b11001001001 !
b11001001001 #
1"
#49000000
0"
#49500000
b110010 $
b10011000111 !
b10011000111 #
1"
#50000000
0"
#50500000
b110011 $
b0 !
b0 #
1"
#51000000
0"
#51500000
b110100 $
b101100111001 !
b101100111001 #
1"
#52000000
0"
#52500000
b110101 $
b100110110111 !
b100110110111 #
1"
#53000000
0"
#53500000
b110110 $
b100110110101 !
b100110110101 #
1"
#54000000
0"
#54500000
b110111 $
b101100110101 !
b101100110101 #
1"
#55000000
0"
#55500000
b111000 $
b111111111010 !
b111111111010 #
1"
#56000000
0"
#56500000
b111001 $
b10010111110 !
b10010111110 #
1"
#57000000
0"
#57500000
b111010 $
b11001000000 !
b11001000000 #
1"
#58000000
0"
#58500000
b111011 $
b11001000001 !
b11001000001 #
1"
#59000000
0"
#59500000
b111100 $
b10011000011 !
b10011000011 #
1"
#60000000
0"
#60500000
b111101 $
b0 !
b0 #
1"
#61000000
0"
#61500000
b111110 $
b101100111101 !
b101100111101 #
1"
#62000000
0"
#62500000
b111111 $
b100110111111 !
b100110111111 #
1"
#63000000
0"
#63500000
b1000000 $
b100111000000 !
b100111000000 #
1"
#64000000
0"
#64500000
b1000001 $
b101101000010 !
b101101000010 #
1"
#65000000
0"
#65500000
b1000010 $
b110 !
b110 #
1"
#66000000
0"
#66500000
b1000011 $
b10011001011 !
b10011001011 #
1"
#67000000
0"
#67500000
b1000100 $
b11001001011 !
b11001001011 #
1"
#68000000
0"
#68500000
b1000101 $
b11001001001 !
b11001001001 #
1"
#69000000
0"
#69500000
b1000110 $
b10011000111 !
b10011000111 #
1"
#70000000
0"
#70500000
b1000111 $
b0 !
b0 #
1"
#71000000
0"
#71500000
b1001000 $
b101100111001 !
b101100111001 #
1"
#72000000
0"
#72500000
b1001001 $
b100110110111 !
b100110110111 #
1"
#73000000
0"
#73500000
b1001010 $
b100110110101 !
b100110110101 #
1"
#74000000
0"
#74500000
b1001011 $
b101100110101 !
b101100110101 #
1"
#75000000
0"
#75500000
b1001100 $
b111111111010 !
b111111111010 #
1"
#76000000
0"
#76500000
b1001101 $
b10010111110 !
b10010111110 #
1"
#77000000
0"
#77500000
b1001110 $
b11001000000 !
b11001000000 #
1"
#78000000
0"
#78500000
b1001111 $
b11001000001 !
b11001000001 #
1"
#79000000
0"
#79500000
b1010000 $
b10011000011 !
b10011000011 #
1"
#80000000
0"
#80500000
b1010001 $
b0 !
b0 #
1"
#81000000
0"
#81500000
b1010010 $
b101100111101 !
b101100111101 #
1"
#82000000
0"
#82500000
b1010011 $
b100110111111 !
b100110111111 #
1"
#83000000
0"
#83500000
b1010100 $
b100111000000 !
b100111000000 #
1"
#84000000
0"
#84500000
b1010101 $
b101101000010 !
b101101000010 #
1"
#85000000
0"
#85500000
b1010110 $
b110 !
b110 #
1"
#86000000
0"
#86500000
b1010111 $
b10011001011 !
b10011001011 #
1"
#87000000
0"
#87500000
b1011000 $
b11001001011 !
b11001001011 #
1"
#88000000
0"
#88500000
b1011001 $
b11001001001 !
b11001001001 #
1"
#89000000
0"
#89500000
b1011010 $
b10011000111 !
b10011000111 #
1"
#90000000
0"
#90500000
b1011011 $
b0 !
b0 #
1"
#91000000
0"
#91500000
b1011100 $
b101100111001 !
b101100111001 #
1"
#92000000
0"
#92500000
b1011101 $
b100110110111 !
b100110110111 #
1"
#93000000
0"
#93500000
b1011110 $
b100110110101 !
b100110110101 #
1"
#94000000
0"
#94500000
b1011111 $
b101100110101 !
b101100110101 #
1"
#95000000
0"
#95500000
b1100000 $
b111111111010 !
b111111111010 #
1"
#96000000
0"
#96500000
b1100001 $
b10010111110 !
b10010111110 #
1"
#97000000
0"
#97500000
b1100010 $
b11001000000 !
b11001000000 #
1"
#98000000
0"
#98500000
b1100011 $
b11001000001 !
b11001000001 #
1"
#99000000
0"
#99500000
b1100100 $
b10011000011 !
b10011000011 #
1"
#100000000
0"
#100500000
b1100101 $
b0 !
b0 #
1"
#101000000
0"
#101500000
b1100110 $
b101100111101 !
b101100111101 #
1"
#102000000
0"
#102500000
b1100111 $
b100110111111 !
b100110111111 #
1"
#103000000
0"
#103500000
b1101000 $
b100111000000 !
b100111000000 #
1"
#104000000
0"
#104500000
b1101001 $
b101101000010 !
b101101000010 #
1"
#105000000
0"
#105500000
b1101010 $
b110 !
b110 #
1"
#106000000
0"
#106500000
b1101011 $
b10011001011 !
b10011001011 #
1"
#107000000
0"
#107500000
b1101100 $
b11001001011 !
b11001001011 #
1"
#108000000
0"
#108500000
b1101101 $
b11001001001 !
b11001001001 #
1"
#109000000
0"
#109500000
b1101110 $
b10011000111 !
b10011000111 #
1"
#110000000
0"
#110500000
b1101111 $
b0 !
b0 #
1"
#111000000
0"
#111500000
b1110000 $
b101100111001 !
b101100111001 #
1"
#112000000
0"
#112500000
b1110001 $
b100110110111 !
b100110110111 #
1"
#113000000
0"
#113500000
b1110010 $
b100110110101 !
b100110110101 #
1"
#114000000
0"
#114500000
b1110011 $
b101100110101 !
b101100110101 #
1"
#115000000
0"
#115500000
b1110100 $
b111111111010 !
b111111111010 #
1"
#116000000
0"
#116500000
b1110101 $
b10010111110 !
b10010111110 #
1"
#117000000
0"
#117500000
b1110110 $
b11001000000 !
b11001000000 #
1"
#118000000
0"
#118500000
b1110111 $
b11001000001 !
b11001000001 #
1"
#119000000
0"
#119500000
b1111000 $
b10011000011 !
b10011000011 #
1"
#120000000
0"
#120500000
b1111001 $
b0 !
b0 #
1"
#121000000
0"
#121500000
b1111010 $
b101100111101 !
b101100111101 #
1"
#122000000
0"
#122500000
b1111011 $
b100110111111 !
b100110111111 #
1"
#123000000
0"
#123500000
b1111100 $
b100111000000 !
b100111000000 #
1"
#124000000
0"
#124500000
b1111101 $
b101101000010 !
b101101000010 #
1"
#125000000
0"
#125500000
b1111110 $
b110 !
b110 #
1"
#126000000
0"
#126500000
b1111111 $
b10011001011 !
b10011001011 #
1"
#127000000
0"
#127500000
b10000000 $
b11001001011 !
b11001001011 #
1"
#128000000
0"
#128500000
b10000001 $
b11001001001 !
b11001001001 #
1"
#129000000
0"
#129500000
b10000010 $
b10011000111 !
b10011000111 #
1"
#130000000
0"
#130500000
b10000011 $
b0 !
b0 #
1"
#131000000
0"
#131500000
b10000100 $
b101100111001 !
b101100111001 #
1"
#132000000
0"
#132500000
b10000101 $
b100110110111 !
b100110110111 #
1"
#133000000
0"
#133500000
b10000110 $
b100110110101 !
b100110110101 #
1"
#134000000
0"
#134500000
b10000111 $
b101100110101 !
b101100110101 #
1"
#135000000
0"
#135500000
b10001000 $
b111111111010 !
b111111111010 #
1"
#136000000
0"
#136500000
b10001001 $
b10010111110 !
b10010111110 #
1"
#137000000
0"
#137500000
b10001010 $
b11001000000 !
b11001000000 #
1"
#138000000
0"
#138500000
b10001011 $
b11001000001 !
b11001000001 #
1"
#139000000
0"
#139500000
b10001100 $
b10011000011 !
b10011000011 #
1"
#140000000
0"
#140500000
b10001101 $
b0 !
b0 #
1"
#141000000
0"
#141500000
b10001110 $
b101100111101 !
b101100111101 #
1"
#142000000
0"
#142500000
b10001111 $
b100110111111 !
b100110111111 #
1"
#143000000
0"
#143500000
b10010000 $
b100111000000 !
b100111000000 #
1"
#144000000
0"
#144500000
b10010001 $
b101101000010 !
b101101000010 #
1"
#145000000
0"
#145500000
b10010010 $
b110 !
b110 #
1"
#146000000
0"
#146500000
b10010011 $
b10011001011 !
b10011001011 #
1"
#147000000
0"
#147500000
b10010100 $
b11001001011 !
b11001001011 #
1"
#148000000
0"
#148500000
b10010101 $
b11001001001 !
b11001001001 #
1"
#149000000
0"
#149500000
b10010110 $
b10011000111 !
b10011000111 #
1"
#150000000
0"
#150500000
b10010111 $
b0 !
b0 #
1"
#151000000
0"
#151500000
b10011000 $
b101100111001 !
b101100111001 #
1"
#152000000
0"
#152500000
b10011001 $
b100110110111 !
b100110110111 #
1"
#153000000
0"
#153500000
b10011010 $
b100110110101 !
b100110110101 #
1"
#154000000
0"
#154500000
b10011011 $
b101100110101 !
b101100110101 #
1"
#155000000
0"
#155500000
b10011100 $
b111111111010 !
b111111111010 #
1"
#156000000
0"
#156500000
b10011101 $
b10010111110 !
b10010111110 #
1"
#157000000
0"
#157500000
b10011110 $
b11001000000 !
b11001000000 #
1"
#158000000
0"
#158500000
b10011111 $
b11001000001 !
b11001000001 #
1"
#159000000
0"
#159500000
b10100000 $
b10011000011 !
b10011000011 #
1"
#160000000
0"
#160500000
b10100001 $
b0 !
b0 #
1"
#161000000
0"
#161500000
b10100010 $
b101100111101 !
b101100111101 #
1"
#162000000
0"
#162500000
b10100011 $
b100110111111 !
b100110111111 #
1"
#163000000
0"
#163500000
b10100100 $
b100111000000 !
b100111000000 #
1"
#164000000
0"
#164500000
b10100101 $
b101101000010 !
b101101000010 #
1"
#165000000
0"
#165500000
b10100110 $
b110 !
b110 #
1"
#166000000
0"
#166500000
b10100111 $
b10011001011 !
b10011001011 #
1"
#167000000
0"
#167500000
b10101000 $
b11001001011 !
b11001001011 #
1"
#168000000
0"
#168500000
b10101001 $
b11001001001 !
b11001001001 #
1"
#169000000
0"
#169500000
b10101010 $
b10011000111 !
b10011000111 #
1"
#170000000
0"
#170500000
b10101011 $
b0 !
b0 #
1"
#171000000
0"
#171500000
b10101100 $
b101100111001 !
b101100111001 #
1"
#172000000
0"
#172500000
b10101101 $
b100110110111 !
b100110110111 #
1"
#173000000
0"
#173500000
b10101110 $
b100110110101 !
b100110110101 #
1"
#174000000
0"
#174500000
b10101111 $
b101100110101 !
b101100110101 #
1"
#175000000
0"
#175500000
b10110000 $
b111111111010 !
b111111111010 #
1"
#176000000
0"
#176500000
b10110001 $
b10010111110 !
b10010111110 #
1"
#177000000
0"
#177500000
b10110010 $
b11001000000 !
b11001000000 #
1"
#178000000
0"
#178500000
b10110011 $
b11001000001 !
b11001000001 #
1"
#179000000
0"
#179500000
b10110100 $
b10011000011 !
b10011000011 #
1"
#180000000
0"
#180500000
b10110101 $
b0 !
b0 #
1"
#181000000
0"
#181500000
b10110110 $
b101100111101 !
b101100111101 #
1"
#182000000
0"
#182500000
b10110111 $
b100110111111 !
b100110111111 #
1"
#183000000
0"
#183500000
b10111000 $
b100111000000 !
b100111000000 #
1"
#184000000
0"
#184500000
b10111001 $
b101101000010 !
b101101000010 #
1"
#185000000
0"
#185500000
b10111010 $
b110 !
b110 #
1"
#186000000
0"
#186500000
b10111011 $
b10011001011 !
b10011001011 #
1"
#187000000
0"
#187500000
b10111100 $
b11001001011 !
b11001001011 #
1"
#188000000
0"
#188500000
b10111101 $
b11001001001 !
b11001001001 #
1"
#189000000
0"
#189500000
b10111110 $
b10011000111 !
b10011000111 #
1"
#190000000
0"
#190500000
b10111111 $
b0 !
b0 #
1"
#191000000
0"
#191500000
b11000000 $
b101100111001 !
b101100111001 #
1"
#192000000
0"
#192500000
b11000001 $
b100110110111 !
b100110110111 #
1"
#193000000
0"
#193500000
b11000010 $
b100110110101 !
b100110110101 #
1"
#194000000
0"
#194500000
b11000011 $
b101100110101 !
b101100110101 #
1"
#195000000
0"
#195500000
b11000100 $
b111111111010 !
b111111111010 #
1"
#196000000
0"
#196500000
b11000101 $
b10010111110 !
b10010111110 #
1"
#197000000
0"
#197500000
b11000110 $
b11001000000 !
b11001000000 #
1"
#198000000
0"
#198500000
b11000111 $
b11001000001 !
b11001000001 #
1"
#199000000
0"
#199500000
b11001000 $
b10011000011 !
b10011000011 #
1"
#200000000
0"
#200500000
b11001001 $
b0 !
b0 #
1"
#201000000
0"
#201500000
b11001010 $
b101100111101 !
b101100111101 #
1"
#202000000
0"
#202500000
b11001011 $
b100110111111 !
b100110111111 #
1"
#203000000
0"
#203500000
b11001100 $
b100111000000 !
b100111000000 #
1"
#204000000
0"
#204500000
b11001101 $
b101101000010 !
b101101000010 #
1"
#205000000
0"
#205500000
b11001110 $
b110 !
b110 #
1"
#206000000
0"
#206500000
b11001111 $
b10011001011 !
b10011001011 #
1"
#207000000
0"
#207500000
b11010000 $
b11001001011 !
b11001001011 #
1"
#208000000
0"
#208500000
b11010001 $
b11001001001 !
b11001001001 #
1"
#209000000
0"
#209500000
b11010010 $
b10011000111 !
b10011000111 #
1"
#210000000
0"
#210500000
b11010011 $
b0 !
b0 #
1"
#211000000
0"
#211500000
b11010100 $
b101100111001 !
b101100111001 #
1"
#212000000
0"
#212500000
b11010101 $
b100110110111 !
b100110110111 #
1"
#213000000
0"
#213500000
b11010110 $
b100110110101 !
b100110110101 #
1"
#214000000
0"
#214500000
b11010111 $
b101100110101 !
b101100110101 #
1"
#215000000
0"
#215500000
b11011000 $
b111111111010 !
b111111111010 #
1"
#216000000
0"
#216500000
b11011001 $
b10010111110 !
b10010111110 #
1"
#217000000
0"
#217500000
b11011010 $
b11001000000 !
b11001000000 #
1"
#218000000
0"
#218500000
b11011011 $
b11001000001 !
b11001000001 #
1"
#219000000
0"
#219500000
b11011100 $
b10011000011 !
b10011000011 #
1"
#220000000
0"
#220500000
b11011101 $
b0 !
b0 #
1"
#221000000
0"
#221500000
b11011110 $
b101100111101 !
b101100111101 #
1"
#222000000
0"
#222500000
b11011111 $
b100110111111 !
b100110111111 #
1"
#223000000
0"
#223500000
b11100000 $
b100111000000 !
b100111000000 #
1"
#224000000
0"
#224500000
b11100001 $
b101101000010 !
b101101000010 #
1"
#225000000
0"
#225500000
b11100010 $
b110 !
b110 #
1"
#226000000
0"
#226500000
b11100011 $
b10011001011 !
b10011001011 #
1"
#227000000
0"
#227500000
b11100100 $
b11001001011 !
b11001001011 #
1"
#228000000
0"
#228500000
b11100101 $
b11001001001 !
b11001001001 #
1"
#229000000
0"
#229500000
b11100110 $
b10011000111 !
b10011000111 #
1"
#230000000
0"
#230500000
b11100111 $
b0 !
b0 #
1"
#231000000
0"
#231500000
b11101000 $
b101100111001 !
b101100111001 #
1"
#232000000
0"
#232500000
b11101001 $
b100110110111 !
b100110110111 #
1"
#233000000
0"
#233500000
b11101010 $
b100110110101 !
b100110110101 #
1"
#234000000
0"
#234500000
b11101011 $
b101100110101 !
b101100110101 #
1"
#235000000
0"
#235500000
b11101100 $
b111111111010 !
b111111111010 #
1"
#236000000
0"
#236500000
b11101101 $
b10010111110 !
b10010111110 #
1"
#237000000
0"
#237500000
b11101110 $
b11001000000 !
b11001000000 #
1"
#238000000
0"
#238500000
b11101111 $
b11001000001 !
b11001000001 #
1"
#239000000
0"
#239500000
b11110000 $
b10011000011 !
b10011000011 #
1"
#240000000
0"
#240500000
b11110001 $
b0 !
b0 #
1"
#241000000
0"
#241500000
b11110010 $
b101100111101 !
b101100111101 #
1"
#242000000
0"
#242500000
b11110011 $
b100110111111 !
b100110111111 #
1"
#243000000
0"
#243500000
b11110100 $
b100111000000 !
b100111000000 #
1"
#244000000
0"
#244500000
b11110101 $
b101101000010 !
b101101000010 #
1"
#245000000
0"
#245500000
b11110110 $
b110 !
b110 #
1"
#246000000
0"
#246500000
b11110111 $
b10011001011 !
b10011001011 #
1"
#247000000
0"
#247500000
b11111000 $
b11001001011 !
b11001001011 #
1"
#248000000
0"
#248500000
b11111001 $
b11001001001 !
b11001001001 #
1"
#249000000
0"
#249500000
b11111010 $
b10011000111 !
b10011000111 #
1"
#250000000
0"
#250500000
b11111011 $
b0 !
b0 #
1"
#251000000
0"
#251500000
b11111100 $
b101100111001 !
b101100111001 #
1"
#252000000
0"
#252500000
b11111101 $
b100110110111 !
b100110110111 #
1"
#253000000
0"
#253500000
b11111110 $
b100110110101 !
b100110110101 #
1"
#254000000
0"
#254500000
b11111111 $
b101100110101 !
b101100110101 #
1"
#255000000
0"
#255500000
b100000000 $
b111111111010 !
b111111111010 #
1"
#256000000
0"
#256500000
b100000001 $
b10010111110 !
b10010111110 #
1"
#257000000
0"
#257500000
b100000010 $
b11001000000 !
b11001000000 #
1"
#258000000
0"
#258500000
b100000011 $
b11001000001 !
b11001000001 #
1"
#259000000
0"
#259500000
b100000100 $
b10011000011 !
b10011000011 #
1"
#260000000
0"
#260500000
b100000101 $
b0 !
b0 #
1"
#261000000
0"
#261500000
b100000110 $
b101100111101 !
b101100111101 #
1"
#262000000
0"
#262500000
b100000111 $
b100110111111 !
b100110111111 #
1"
#263000000
0"
#263500000
b100001000 $
b100111000000 !
b100111000000 #
1"
#264000000
0"
#264500000
b100001001 $
b101101000010 !
b101101000010 #
1"
#265000000
0"
#265500000
b100001010 $
b110 !
b110 #
1"
#266000000
0"
#266500000
b100001011 $
b10011001011 !
b10011001011 #
1"
#267000000
0"
#267500000
b100001100 $
b11001001011 !
b11001001011 #
1"
#268000000
0"
#268500000
b100001101 $
b11001001001 !
b11001001001 #
1"
#269000000
0"
#269500000
b100001110 $
b10011000111 !
b10011000111 #
1"
#270000000
0"
#270500000
b100001111 $
b0 !
b0 #
1"
#271000000
0"
#271500000
b100010000 $
b101100111001 !
b101100111001 #
1"
#272000000
0"
#272500000
b100010001 $
b100110110111 !
b100110110111 #
1"
#273000000
0"
#273500000
b100010010 $
b100110110101 !
b100110110101 #
1"
#274000000
0"
#274500000
b100010011 $
b101100110101 !
b101100110101 #
1"
#275000000
0"
#275500000
b100010100 $
b111111111010 !
b111111111010 #
1"
#276000000
0"
#276500000
b100010101 $
b10010111110 !
b10010111110 #
1"
#277000000
0"
#277500000
b100010110 $
b11001000000 !
b11001000000 #
1"
#278000000
0"
#278500000
b100010111 $
b11001000001 !
b11001000001 #
1"
#279000000
0"
#279500000
b100011000 $
b10011000011 !
b10011000011 #
1"
#280000000
0"
#280500000
b100011001 $
b0 !
b0 #
1"
#281000000
0"
#281500000
b100011010 $
b101100111101 !
b101100111101 #
1"
#282000000
0"
#282500000
b100011011 $
b100110111111 !
b100110111111 #
1"
#283000000
0"
#283500000
b100011100 $
b100111000000 !
b100111000000 #
1"
#284000000
0"
#284500000
b100011101 $
b101101000010 !
b101101000010 #
1"
#285000000
0"
#285500000
b100011110 $
b110 !
b110 #
1"
#286000000
0"
#286500000
b100011111 $
b10011001011 !
b10011001011 #
1"
#287000000
0"
#287500000
b100100000 $
b11001001011 !
b11001001011 #
1"
#288000000
0"
#288500000
b100100001 $
b11001001001 !
b11001001001 #
1"
#289000000
0"
#289500000
b100100010 $
b10011000111 !
b10011000111 #
1"
#290000000
0"
#290500000
b100100011 $
b0 !
b0 #
1"
#291000000
0"
#291500000
b100100100 $
b101100111001 !
b101100111001 #
1"
#292000000
0"
#292500000
b100100101 $
b100110110111 !
b100110110111 #
1"
#293000000
0"
#293500000
b100100110 $
b100110110101 !
b100110110101 #
1"
#294000000
0"
#294500000
b100100111 $
b101100110101 !
b101100110101 #
1"
#295000000
0"
#295500000
b100101000 $
b111111111010 !
b111111111010 #
1"
#296000000
0"
#296500000
b100101001 $
b10010111110 !
b10010111110 #
1"
#297000000
0"
#297500000
b100101010 $
b11001000000 !
b11001000000 #
1"
#298000000
0"
#298500000
b100101011 $
b11001000001 !
b11001000001 #
1"
#299000000
0"
#299500000
b100101100 $
b10011000011 !
b10011000011 #
1"
#300000000
0"
#300500000
b100101101 $
b0 !
b0 #
1"
#301000000
0"
#301500000
b100101110 $
b101100111101 !
b101100111101 #
1"
#302000000
0"
#302500000
b100101111 $
b100110111111 !
b100110111111 #
1"
#303000000
0"
#303500000
b100110000 $
b100111000000 !
b100111000000 #
1"
#304000000
0"
#304500000
b100110001 $
b101101000010 !
b101101000010 #
1"
#305000000
0"
#305500000
b100110010 $
b110 !
b110 #
1"
#306000000
0"
#306500000
b100110011 $
b10011001011 !
b10011001011 #
1"
#307000000
0"
#307500000
b100110100 $
b11001001011 !
b11001001011 #
1"
#308000000
0"
#308500000
b100110101 $
b11001001001 !
b11001001001 #
1"
#309000000
0"
#309500000
b100110110 $
b10011000111 !
b10011000111 #
1"
#310000000
0"
#310500000
b100110111 $
b0 !
b0 #
1"
#311000000
0"
#311500000
b100111000 $
b101100111001 !
b101100111001 #
1"
#312000000
0"
#312500000
b100111001 $
b100110110111 !
b100110110111 #
1"
#313000000
0"
#313500000
b100111010 $
b100110110101 !
b100110110101 #
1"
#314000000
0"
#314500000
b100111011 $
b101100110101 !
b101100110101 #
1"
#315000000
0"
#315500000
b100111100 $
b111111111010 !
b111111111010 #
1"
#316000000
0"
#316500000
b100111101 $
b10010111110 !
b10010111110 #
1"
#317000000
0"
#317500000
b100111110 $
b11001000000 !
b11001000000 #
1"
#318000000
0"
#318500000
b100111111 $
b11001000001 !
b11001000001 #
1"
#319000000
0"
#319500000
b101000000 $
b10011000011 !
b10011000011 #
1"
#320000000
0"
#320500000
b101000001 $
b0 !
b0 #
1"
#321000000
0"
#321500000
b101000010 $
b101100111101 !
b101100111101 #
1"
#322000000
0"
#322500000
b101000011 $
b100110111111 !
b100110111111 #
1"
#323000000
0"
#323500000
b101000100 $
b100111000000 !
b100111000000 #
1"
#324000000
0"
#324500000
b101000101 $
b101101000010 !
b101101000010 #
1"
#325000000
0"
#325500000
b101000110 $
b110 !
b110 #
1"
#326000000
0"
#326500000
b101000111 $
b10011001011 !
b10011001011 #
1"
#327000000
0"
#327500000
b101001000 $
b11001001011 !
b11001001011 #
1"
#328000000
0"
#328500000
b101001001 $
b11001001001 !
b11001001001 #
1"
#329000000
0"
#329500000
b101001010 $
b10011000111 !
b10011000111 #
1"
#330000000
0"
#330500000
b101001011 $
b0 !
b0 #
1"
#331000000
0"
#331500000
b101001100 $
b101100111001 !
b101100111001 #
1"
#332000000
0"
#332500000
b101001101 $
b100110110111 !
b100110110111 #
1"
#333000000
0"
#333500000
b101001110 $
b100110110101 !
b100110110101 #
1"
#334000000
0"
#334500000
b101001111 $
b101100110101 !
b101100110101 #
1"
#335000000
0"
#335500000
b101010000 $
b111111111010 !
b111111111010 #
1"
#336000000
0"
#336500000
b101010001 $
b10010111110 !
b10010111110 #
1"
#337000000
0"
#337500000
b101010010 $
b11001000000 !
b11001000000 #
1"
#338000000
0"
#338500000
b101010011 $
b11001000001 !
b11001000001 #
1"
#339000000
0"
#339500000
b101010100 $
b10011000011 !
b10011000011 #
1"
#340000000
0"
#340500000
b101010101 $
b0 !
b0 #
1"
#341000000
0"
#341500000
b101010110 $
b101100111101 !
b101100111101 #
1"
#342000000
0"
#342500000
b101010111 $
b100110111111 !
b100110111111 #
1"
#343000000
0"
#343500000
b101011000 $
b100111000000 !
b100111000000 #
1"
#344000000
0"
#344500000
b101011001 $
b101101000010 !
b101101000010 #
1"
#345000000
0"
#345500000
b101011010 $
b110 !
b110 #
1"
#346000000
0"
#346500000
b101011011 $
b10011001011 !
b10011001011 #
1"
#347000000
0"
#347500000
b101011100 $
b11001001011 !
b11001001011 #
1"
#348000000
0"
#348500000
b101011101 $
b11001001001 !
b11001001001 #
1"
#349000000
0"
#349500000
b101011110 $
b10011000111 !
b10011000111 #
1"
#350000000
0"
#350500000
b101011111 $
b0 !
b0 #
1"
#351000000
0"
#351500000
b101100000 $
b101100111001 !
b101100111001 #
1"
#352000000
0"
#352500000
b101100001 $
b100110110111 !
b100110110111 #
1"
#353000000
0"
#353500000
b101100010 $
b100110110101 !
b100110110101 #
1"
#354000000
0"
#354500000
b101100011 $
b101100110101 !
b101100110101 #
1"
#355000000
0"
#355500000
b101100100 $
b111111111010 !
b111111111010 #
1"
#356000000
0"
#356500000
b101100101 $
b10010111110 !
b10010111110 #
1"
#357000000
0"
#357500000
b101100110 $
b11001000000 !
b11001000000 #
1"
#358000000
0"
#358500000
b101100111 $
b11001000001 !
b11001000001 #
1"
#359000000
0"
#359500000
b101101000 $
b10011000011 !
b10011000011 #
1"
#360000000
0"
#360500000
b101101001 $
b0 !
b0 #
1"
#361000000
0"
#361500000
b101101010 $
b101100111101 !
b101100111101 #
1"
#362000000
0"
#362500000
b101101011 $
b100110111111 !
b100110111111 #
1"
#363000000
0"
#363500000
b101101100 $
b100111000000 !
b100111000000 #
1"
#364000000
0"
#364500000
b101101101 $
b101101000010 !
b101101000010 #
1"
#365000000
0"
#365500000
b101101110 $
b110 !
b110 #
1"
#366000000
0"
#366500000
b101101111 $
b10011001011 !
b10011001011 #
1"
#367000000
0"
#367500000
b101110000 $
b11001001011 !
b11001001011 #
1"
#368000000
0"
#368500000
b101110001 $
b11001001001 !
b11001001001 #
1"
#369000000
0"
#369500000
b101110010 $
b10011000111 !
b10011000111 #
1"
#370000000
0"
#370500000
b101110011 $
b0 !
b0 #
1"
#371000000
0"
#371500000
b101110100 $
b101100111001 !
b101100111001 #
1"
#372000000
0"
#372500000
b101110101 $
b100110110111 !
b100110110111 #
1"
#373000000
0"
#373500000
b101110110 $
b100110110101 !
b100110110101 #
1"
#374000000
0"
#374500000
b101110111 $
b101100110101 !
b101100110101 #
1"
#375000000
0"
#375500000
b101111000 $
b111111111010 !
b111111111010 #
1"
#376000000
0"
#376500000
b101111001 $
b10010111110 !
b10010111110 #
1"
#377000000
0"
