full_adder/full_adder.v
module full_adder(A,B,cin,cout,sum);
    input A, B, cin;
    output cout, sum;

    assign sum = A ^ B ^ cin;
    assign cout = (A & B) | (B & cin) | (A & cin);
endmodule

full_adder/full_adder_tb.v
module full_adder_tb;
    reg A, B, cin;
    wire cout, sum;

    full_adder full_adder_inst(A, B, cin, cout, sum);

    initial begin
        A = 0; B = 0; cin = 0;
        #10 A = 0; B = 0; cin = 1;
        #10 A = 0; B = 1; cin = 0;
        #10 A = 0; B = 1; cin = 1;
        #10 A = 1; B = 0; cin = 0;
        #10 A = 1; B = 0; cin = 1;
        #10 A = 1; B = 1; cin = 0;
        #10 A = 1; B = 1; cin = 1;
        #10 $finish;
    end

    initial begin
        $dumpfile("full_adder_tb.vcd");
        $dumpvars(0, full_adder_tb);
    end

endmodule

full_adder/full_adder_tb.vcd
$date
	Thu Jun 20 00:55:00 2024
$end
$version
	Icarus Verilog
$end
$timescale
	1s
$end
$scope module full_adder_tb $end
$var wire 1 ! sum $end
$var wire 1 " cout $end
$var reg 1 # A $end
$var reg 1 $ B $end
$var reg 1 % cin $end
$scope module full_adder_inst $end
$var wire 1 # A $end
$var wire 1 $ B $end
$var wire 1 % cin $end
$var wire 1 " cout $end
$var wire 1 ! sum $end
$upscope $end
$upscope $end
$enddefinitions $end
$comment Show the parameter values. $end
$dumpall
$end
#0
$dumpvars
0%
0$
0#
0"
0!
$end
#10
1!
1%
#20
0%
1$
#30
1"
0!
1%
#40
0"
1!
0%
0$
1#
#50
1"
0!
1%
#60
0%
1$
#70
1!
1%
